Metadata-Version: 1.1
Name: mytsgraph
Version: 1.0.1
Summary: MySQL table space monitoring.
Home-page: https://github.com/dalenys/mytsgraph
Author: Jérémy Cohen Solal
Author-email: jeremy.cohen-solal@dalenys.com
License: MIT
Platform: UNKNOWN
Classifier: Intended Audience :: Developers
Classifier: Operating System :: OS Independent
Classifier: Programming Language :: Python
Classifier: Programming Language :: Python :: 2
Classifier: Topic :: Software Development :: Libraries :: Python Modules
Classifier: Topic :: Database :: Database Engines/Servers
Classifier: Topic :: System :: Monitoring
Classifier: Topic :: Utilities
